setup.py
makeitgreen.egg-info/PKG-INFO
makeitgreen.egg-info/SOURCES.txt
makeitgreen.egg-info/dependency_links.txt
makeitgreen.egg-info/not-zip-safe
makeitgreen.egg-info/top_level.txt
mig/__init__.py