Metadata-Version: 1.0
Name: makeitgreen
Version: 0.5
Summary: Makes your Git Green every time you run this package
Home-page: https://github.com/arjun921/MakeItGreen
Author: Arjun S
Author-email: arjun.mi1@iiitmk.ac.in
License: UNKNOWN
Platform: UNKNOWN
